{
    "main event": "A UFO sighting report from Monte Vista, Colorado in December 1948.",
    "interesting points": "The incident is numbered 1747,The information is classified as unclassified,The report is sourced from a civilian,The date of observation is mentioned but not clearly visible,The length of observation details are noted but not legible.",
    "sighted object": "unknown",
    "location": "Monte Vista, Colorado, USA",
    "number of confirmed witnesses": 0,
    "witness description": "Civilian source",
    "contains photographs": false
}