{
    "main event": "An OSI agent observed a spheroid-shaped object that was evidently an ascending balloon at Dobbins AFB.",
    "interesting points": "The sighting occurred on February 6, 1952., The observation lasted for 1 unit of time., There was one object observed., The object was recovered after the sighting., The conclusion drawn was that the object was a balloon.",
    "sighted object": "spheroid-shaped object",
    "location": "Dobbins AFB, Georgia, USA",
    "number of confirmed witnesses": 1,
    "witness description": "OSI agent",
    "contains photographs": true
}