{
    "main event": "A sighting of a white, oblong, rigid object was reported in Washington, D.C. on March 22, 1958.",
    "interesting points": "The object exhibited an erratic flight path during the observation., The sighting lasted for 3 minutes., The observation was made at 9:15 p.m., The type of observation was ground-visual., The object's description is characterized as typical for UFO sightings.",
    "sighted object": "one oblong rigid object",
    "location": "Washington, D.C.",
    "number of confirmed witnesses": 0,
    "witness description": "not specified",
    "contains photographs": false
}