{
    "main event": "A bright star-like object was sighted due East of Miami on July 17, 1958.",
    "interesting points": "The object was reported to be approximately 20 times the size of a star.,It was noted to be motionless and very brilliant.,Witnesses estimated its elevation to be 20-30 degrees.,The object slowly disappeared from sight.,The local police and Project Blue Book were involved in documenting the sighting.",
    "sighted object": "bright star-like object",
    "location": "Miami, Florida, USA",
    "number of confirmed witnesses": 1,
    "witness description": "Miami Police Sgt Regan",
    "contains photographs": false
}