{
    "main event": "Several objects were sighted described as semi-circular in shape, connected by a faint cloud, and pulsing with bright green and orange colors on February 15, 1952.",
    "interesting points": "The sighting lasted for approximately 15 minutes,Witness observed the objects from their backyard for about 3 seconds before they dispersed in different directions,The objects emitted a slight humming noise,Objects appeared like clouds and were described as metallic,Conclusions considered various possibilities for the objects including balloon or astronomical phenomena.",
    "sighted object": "multiple semi-circular objects with pulsing lights",
    "location": "Springfield, Ohio, USA",
    "number of confirmed witnesses": 1,
    "witness description": "Witness viewed the objects from their backyard.",
    "contains photographs": false
}