{
    "main event": "Multiple military observers reported sighting multiple objects performing circular directional movements 75 miles NW of Midway Island.",
    "interesting points": "The objects were initially thought to be meteor showers., Observation lasted from 161440Z to 1557Z., Estimated altitude above 20,000 feet., There were multiple military observers involved in the report., Physical evidence was noted in the report.",
    "sighted object": "multiple unidentified flying objects",
    "location": "75 Miles NW of Midway Island",
    "number of confirmed witnesses": 0,
    "witness description": "multiple military observers",
    "contains photographs": true
}