{
    "main event": "A civilian witnessed a UFO described as a yellow light changing to orange and then blue-green in Des Moines, Iowa on August 5, 1965.",
    "interesting points": "The sighting lasted for over 15 minutes,The object was first noticed glowing but this feature wasn't evident upon closer observation with binoculars,The object had no tail, trail, or exhaust and made no sound,Initial altitude was estimated between 15,000 and 20,000 feet and ended at 8,000 feet,The UFO's course was slightly erratic and it disappeared instantaneously.",
    "sighted object": "yellow light changing to orange and then blue-green",
    "location": "Des Moines, Iowa, USA",
    "number of confirmed witnesses": 1,
    "witness description": "a 15-year-old civilian and his father (age 34)",
    "contains photographs": false
}