{
    "main event": "A military source reported a stationary white object observed on September 24, 1966.",
    "interesting points": "The object was observed visually without any physical evidence., The location of the observation included multiple states: Alabama, Arkansas, Ohio, and Louisiana., The object was reported to be one in number., The duration of the observation was visual., The explanation given for the sighting was categorized as 'Other' with an emphasis on proximity to the observer.",
    "sighted object": "one stationary white object",
    "location": "Alabama, Arkansas, Ohio, Louisiana, USA",
    "number of confirmed witnesses": 0,
    "witness description": "military source",
    "contains photographs": false
}