{
    "main event": "A Project Blue Book report from January 1967 regarding two riders in Camarillo, California, contains details about packaging and seals but lacks photographic content.",
    "interesting points": "The report is from Project Blue Book, which studied UFO sightings., The document features instructions about sealing boxes with a warm iron., Two riders were mentioned but their observations are not detailed., There is handwritten text present but it's not decipherable., The report seems to focus on packaging rather than a UFO sighting.",
    "sighted object": "none described",
    "location": "Camarillo, California, USA",
    "number of confirmed witnesses": 2,
    "witness description": "riders in the area",
    "contains photographs": false
}