{
    "main event": "A bright object was observed approaching from the west, slowing down, and then disappearing behind trees in the distance.",
    "interesting points": [
        "The observation was made using both ground radar and visual means.",
        "The object was described as 'black' in color.",
        "The observation lasted for approximately 0.5 hours.",
        "The report notes that there was insufficient data to evaluate the sighting.",
        "The conclusion was that the sighting was 'Unknown'."
    ],
    "result": "unknown",
    "sighted object": "a bright black object",
    "location": "Madeira, Ohio",
    "witnesses": "civilian",
    "photographs": "yes, the report includes photographs"
}